foldermerge-0.4.0.dist-info/METADATA
foldermerge-0.4.0.dist-info/WHEEL
foldermerge-0.4.0.dist-info/entry_points.txt
foldermerge-0.4.0.dist-info/licenses/LICENSE
foldermerge/__init__.py
foldermerge/core.py
foldermerge/custom_accessors.py
foldermerge/gui/flask.py
foldermerge/gui/static/css/files_view_style.css
foldermerge/gui/static/css/index_style.css
foldermerge/gui/static/favicon.svg
foldermerge/gui/static/js/files_view_script.js
foldermerge/gui/static/js/index_script.js
foldermerge/gui/static/js/report_view_script.js
foldermerge/gui/templates/files_view.html
foldermerge/gui/templates/index.html
foldermerge/gui/templates/report_view.html
foldermerge-0.4.0.dist-info/RECORD
