Metadata-Version: 2.1
Name: foldermerge
Version: 0.4.0
Summary: Default template for PDM package
Author-Email: JostTim <44769559+JostTim@users.noreply.github.com>
License: MIT
Requires-Python: <3.13,>=3.12
Requires-Dist: pandas>=2.1.4
Requires-Dist: tqdm>=4.66.1
Requires-Dist: flask>=3.0.2; extra == "gui"
Provides-Extra: gui
